copy_ai_mcp/__init__.py
copy_ai_mcp/schema.json
copy_ai_mcp/server.py
copy_ai_mcp-0.1.1.dist-info/LICENSE
copy_ai_mcp-0.1.1.dist-info/METADATA
copy_ai_mcp-0.1.1.dist-info/WHEEL
copy_ai_mcp-0.1.1.dist-info/entry_points.txt
copy_ai_mcp-0.1.1.dist-info/RECORD
