Metadata-Version: 2.3
Name: copy-ai-mcp
Version: 0.1.1
Summary: A MCP server for Copy.ai.
License: MIT
Author: yanrujing
Author-email: rujing.yan@protagonist-ai.com
Requires-Python: >=3.11,<4.0
Classifier: License :: OSI Approved :: MIT License
Classifier: Programming Language :: Python :: 3
Classifier: Programming Language :: Python :: 3.11
Classifier: Programming Language :: Python :: 3.12
Classifier: Programming Language :: Python :: 3.13
Requires-Dist: fastmcp (>=2.11.3,<3.0.0)
